[
  {
    "id": 1,
    "titile": "Young Thug",
    "product": " Young Thug ",
    "category": "T-shirt",
    "image": "/thugga.jpg",
    "price": 400.00,
    "description": "100% cotton",
    "isAvailable": "Yes"
  },
  {
    "id": 1,
    "titile": "Vans",
    "product": " Vans ",
    "category": "Sneaker",
    "image": "https://images.unsplash.com/photo-1626379530580-6a58c5cf1d5e?q=80&w=2574&auto=format&fit=crop&ixlib=rb-4.0.3&ixid=M3wxMjA3fDB8MHxwaG90by1wYWdlfHx8fGVufDB8fHx8fA%3D%3D",
    "price": 600.00,
    "description": "100% cotton",
    "isAvailable": "Yes"
  },
  {
    "id": 1,
    "titile": "Gildan",
    "product": "Gildan  ",
    "category": "T-shirt",
    "image": "https://images.unsplash.com/photo-1521572163474-6864f9cf17ab?q=80&w=2680&auto=format&fit=crop&ixlib=rb-4.0.3&ixid=M3wxMjA3fDB8MHxwaG90by1wYWdlfHx8fGVufDB8fHx8fA%3D%3D",
    "price": 100.00,
    "description": "100% cotton",
    "isAvailable": "Yes"
  },
  {
  "id": 1,
  "titile": "Adidas",
  "product": " Yeezy ",
  "category": "Sneakers",
  "image": "https://images.unsplash.com/photo-1606297199333-e93f7d726cab?q=80&w=2574&auto=format&fit=crop&ixlib=rb-4.0.3&ixid=M3wxMjA3fDB8MHxwaG90by1wYWdlfHx8fGVufDB8fHx8fA%3D%3D",
  "price": 800.00,
  "description": "100% cotton",
  "isAvailable": "Yes"
  },
  {
  "id": 1,
  "titile": "Adidas",
  "product": " Yeezy ",
  "category": "Sneaker",
  "image": "https://images.unsplash.com/photo-1626771652942-93d834f3d1fd?q=80&w=2565&auto=format&fit=crop&ixlib=rb-4.0.3&ixid=M3wxMjA3fDB8MHxwaG90by1wYWdlfHx8fGVufDB8fHx8fA%3D%3D",
  "price":700.00,
  "description": "100% cotton",
  "isAvailable": "Yes"
  },
  {
    "id": 1,
    "titile": "Young Thug",
    "product": " Young Thug  ",
    "category": "T-shirt",
    "image": "/thugga.jpg",
    "price": 400.00,
    "description": "100% cotton",
    "isAvailable": "Yes"
  }
]